giorgio/__main__.py
giorgio/ai_client.py
giorgio/cli.py
giorgio/execution_engine.py
giorgio/logconfig.py
giorgio/project_manager.py
giorgio/prompt.py
giorgio/ui_cli.py
giorgio/ui_renderer.py
giorgio/validation.py
giorgio/templates/script_template.py
giorgio-1.8.0.data/data/share/doc/giorgio/LICENSE
giorgio-1.8.0.data/data/share/doc/giorgio/README.md
giorgio-1.8.0.dist-info/licenses/LICENSE
giorgio-1.8.0.dist-info/METADATA
giorgio-1.8.0.dist-info/WHEEL
giorgio-1.8.0.dist-info/entry_points.txt
giorgio-1.8.0.dist-info/top_level.txt
giorgio-1.8.0.dist-info/RECORD
