Metadata-Version: 2.4
Name: giorgio
Version: 1.8.0
Summary: Giorgio: a micro-framework for interactive Python scripts
Author-email: Danilo Musci <officina@musci.ch>
License: MIT License
Project-URL: Homepage, https://github.com/officinaMusci/giorgio
Project-URL: Documentation, https://github.com/officinaMusci/giorgio#readme
Project-URL: Repository, https://github.com/officinaMusci/giorgio
Project-URL: Issues, https://github.com/officinaMusci/giorgio/issues
Project-URL: Changelog, https://github.com/officinaMusci/giorgio/blob/master/CHANGELOG.md
Keywords: automation,cli,scripts,micro-framework
Classifier: Development Status :: 5 - Production/Stable
Classifier: Environment :: Console
Classifier: Intended Audience :: Developers
Classifier: Natural Language :: English
Classifier: Operating System :: OS Independent
Classifier: Programming Language :: Python :: 3.10
Classifier: Programming Language :: Python :: 3.11
Classifier: Programming Language :: Python :: 3.12
Classifier: License :: OSI Approved :: MIT License
Requires-Python: <4.0,>=3.10
License-File: LICENSE
Requires-Dist: typer>=0.9.0
Requires-Dist: questionary>=1.10.0
Requires-Dist: python-dotenv>=1.0.0
Requires-Dist: instructor>=1.0.0
Requires-Dist: openai>=1.0.0
Requires-Dist: rich>=13.0.0
Dynamic: license-file
